plot.py
wavedata.py
wavedata-0.1.dist-info/METADATA
wavedata-0.1.dist-info/WHEEL
wavedata-0.1.dist-info/top_level.txt
wavedata-0.1.dist-info/RECORD
